.hgignore
.hgtags
CHANGES.rst
README.rst
go.sh
pytest.ini
setup.py
sketch/sketch.ino
src/gocept/__init__.py
src/gocept.remoteleds.egg-info/PKG-INFO
src/gocept.remoteleds.egg-info/SOURCES.txt
src/gocept.remoteleds.egg-info/dependency_links.txt
src/gocept.remoteleds.egg-info/entry_points.txt
src/gocept.remoteleds.egg-info/namespace_packages.txt
src/gocept.remoteleds.egg-info/not-zip-safe
src/gocept.remoteleds.egg-info/requires.txt
src/gocept.remoteleds.egg-info/top_level.txt
src/gocept/remoteleds/__init__.py
src/gocept/remoteleds/client.py
src/gocept/remoteleds/config.py
src/gocept/remoteleds/discovery.py
src/gocept/remoteleds/fancy.py
src/gocept/remoteleds/jenkins.py
src/gocept/remoteleds/log.py
src/gocept/remoteleds/tests/__init__.py
src/gocept/remoteleds/tests/test_client.py