Metadata-Version: 1.1
Name: gocept.remoteleds
Version: 1.2
Summary: Can speak to an Arduino and set color of connected LEDs.
Home-page: https://bitbucket.org/gocept/gocept.remoteleds
Author: Daniel Havlik, Florian Pilz and Oliver Zscheyge
Author-email: dh@gocept.com
License: MIT
Keywords: arduino led adafruit neopixel
Platform: UNKNOWN
Classifier: Environment :: Console
Classifier: Intended Audience :: Developers
Classifier: Programming Language :: Python :: 2.7
Classifier: License :: OSI Approved :: MIT License
Classifier: Operating System :: OS Independent
Classifier: Programming Language :: Python
Classifier: Programming Language :: C
Classifier: Topic :: Software Development :: Testing
Classifier: Topic :: Software Development :: Quality Assurance
